python_ulid_django-1.3.0.dist-info/METADATA
python_ulid_django-1.3.0.dist-info/WHEEL
python_ulid_django-1.3.0.dist-info/entry_points.txt
python_ulid_django-1.3.0.dist-info/licenses/LICENSE
ulid_django/__init__.py
ulid_django/converters.py
ulid_django/forms.py
ulid_django/models.py
ulid_django/py.typed
python_ulid_django-1.3.0.dist-info/RECORD
