Metadata-Version: 2.1
Name: python-ulid-django
Version: 1.3.0
Summary: ULID (Universally Unique Lexicographically Sortable Identifier) support for Django.
Author-Email: Xdynix <Lizard.rar@gmail.com>
License: MIT
Classifier: Development Status :: 5 - Production/Stable
Classifier: Framework :: Django
Classifier: Framework :: Django :: 4
Classifier: Framework :: Django :: 5
Classifier: Intended Audience :: Developers
Classifier: License :: OSI Approved :: MIT License
Classifier: Operating System :: OS Independent
Classifier: Programming Language :: Python
Classifier: Programming Language :: Python :: 3
Classifier: Programming Language :: Python :: 3.10
Classifier: Programming Language :: Python :: 3.11
Classifier: Programming Language :: Python :: 3.12
Classifier: Programming Language :: Python :: 3.13
Classifier: Programming Language :: Python :: 3.14
Classifier: Topic :: Software Development :: Libraries
Classifier: Topic :: Software Development :: Libraries :: Python Modules
Project-URL: Homepage, https://github.com/Xdynix/python-ulid-django
Requires-Python: >=3.10
Requires-Dist: django>=4.2.0
Requires-Dist: python-ulid<4.0.0,>=3.0.0
Requires-Dist: typing-extensions>=4.15.0; python_version < "3.12"
